messente_hlr/__init__.py
messente_hlr/api.py
messente_hlr/client.py
messente_hlr/exceptions.py
messente_hlr_lib-0.0.1.dist-info/DESCRIPTION.rst
messente_hlr_lib-0.0.1.dist-info/METADATA
messente_hlr_lib-0.0.1.dist-info/RECORD
messente_hlr_lib-0.0.1.dist-info/WHEEL
messente_hlr_lib-0.0.1.dist-info/metadata.json
messente_hlr_lib-0.0.1.dist-info/top_level.txt
