Metadata-Version: 2.0
Name: messente-hlr-lib
Version: 0.0.1
Summary: Hlr api library
Home-page: UNKNOWN
Author: messente
Author-email: support@messente.com
License: UNKNOWN
Keywords: HLR api library
Platform: UNKNOWN
Requires-Dist: requests (==2.18.4)
